{
  "description": "The Jaeger Receiver receives trace data in the [Jaeger](https://www.jaegertracing.io/) format.",
  "display_name": "Jaeger Receiver",
  "distribution": "contrib",
  "ecosystem": "collector",
  "id": "contrib-jaegerreceiver",
  "name": "jaegerreceiver",
  "repository": "opentelemetry-collector-contrib",
  "status": {
    "class": "receiver",
    "codeowners": {
      "active": [
        "yurishkuro"
      ]
    },
    "distributions": [
      "contrib",
      "core",
      "k8s"
    ],
    "stability": {
      "beta": [
        "traces"
      ]
    }
  },
  "type": "receiver"
}