{
  "description": null,
  "display_name": "Metrics Transform Processor",
  "distribution": "contrib",
  "ecosystem": "collector",
  "id": "contrib-metricstransformprocessor",
  "name": "metricstransformprocessor",
  "repository": "opentelemetry-collector-contrib",
  "status": {
    "class": "processor",
    "codeowners": {
      "active": [
        "dmitryax"
      ]
    },
    "distributions": [
      "contrib",
      "k8s"
    ],
    "stability": {
      "beta": [
        "metrics"
      ]
    }
  },
  "type": "processor"
}